notbank_python_sdk/__init__.py
notbank_python_sdk/client_connection.py
notbank_python_sdk/client_connection_factory.py
notbank_python_sdk/error.py
notbank_python_sdk/notbank_client.py
notbank_python_sdk/notbank_client_cache.py
notbank_python_sdk/parsing.py
notbank_python_sdk/core/__init__.py
notbank_python_sdk/core/ap_data_handler.py
notbank_python_sdk/core/authenticator.py
notbank_python_sdk/core/converter.py
notbank_python_sdk/core/either.py
notbank_python_sdk/core/endpoint_category.py
notbank_python_sdk/core/endpoints.py
notbank_python_sdk/core/response_handler.py
notbank_python_sdk/core/tools.py
notbank_python_sdk/models/__init__.py
notbank_python_sdk/models/account_fee.py
notbank_python_sdk/models/account_info.py
notbank_python_sdk/models/account_positions.py
notbank_python_sdk/models/account_trade.py
notbank_python_sdk/models/account_transaction.py
notbank_python_sdk/models/activity_report.py
notbank_python_sdk/models/address.py
notbank_python_sdk/models/authenticate_2fa.py
notbank_python_sdk/models/authenticate_response.py
notbank_python_sdk/models/bank.py
notbank_python_sdk/models/bank_account.py
notbank_python_sdk/models/cancel_order_reject_event.py
notbank_python_sdk/models/cancel_replace_order_request.py
notbank_python_sdk/models/cbu_owner.py
notbank_python_sdk/models/currency_network_templates.py
notbank_python_sdk/models/deposit_event.py
notbank_python_sdk/models/deposit_fee.py
notbank_python_sdk/models/deposit_ticket.py
notbank_python_sdk/models/document.py
notbank_python_sdk/models/document_slice.py
notbank_python_sdk/models/enums.py
notbank_python_sdk/models/fee.py
notbank_python_sdk/models/fee_id.py
notbank_python_sdk/models/id_response.py
notbank_python_sdk/models/instrument.py
notbank_python_sdk/models/instrument_limits.py
notbank_python_sdk/models/instrument_statistic.py
notbank_python_sdk/models/instrument_summary.py
notbank_python_sdk/models/instrument_verification_level_limits.py
notbank_python_sdk/models/level1_ticker.py
notbank-2.1.0.dist-info/LICENSE
notbank-2.1.0.dist-info/METADATA
notbank-2.1.0.dist-info/WHEEL
notbank-2.1.0.dist-info/top_level.txt
notbank-2.1.0.dist-info/RECORD
