Metadata-Version: 2.1
Name: notbank
Version: 2.1.0
Summary: Notbank API client library
Home-page: https://github.com/notbank-exchange/notbank-python
Author: Notbank
Keywords: api,notbank,cryptomkt,cryptomarket,bitcoin,client,cryptocurrency
Classifier: Intended Audience :: Developers
Classifier: Programming Language :: Python :: 3
Classifier: Programming Language :: Python :: 3.7
Classifier: Programming Language :: Python :: 3 :: Only
Classifier: License :: OSI Approved :: MIT License
Classifier: Operating System :: OS Independent
Classifier: Topic :: Software Development :: Libraries :: Python Modules
Requires-Python: >=3.7
License-File: LICENSE
Requires-Dist: charset-normalizer (==2.0.12)
Requires-Dist: dacite (==1.9.2)
Requires-Dist: idna (==3.3)
Requires-Dist: requests (==2.27.1)
Requires-Dist: simplejson (==3.20.1)
Requires-Dist: typing-extensions (==4.7.1)
Requires-Dist: urllib3 (==1.26.9)
Requires-Dist: websocket-client (==1.6.1)
Requires-Dist: certifi (==2025.7.9) ; python_version >= "3.7"
